verilator_test/test.v
module test(
    input i_clk,
    input i_rst,
    input i_a,
    input i_b,
    output o_f
);
reg ro_f;
assign o_f = ro_f;
always@(posedge i_clk or posedge i_rst)
begin
    if(i_rst)
        ro_f <= 1;
    else
        ro_f <= i_a ^ i_b;
end
endmodule

verilator_test/wave.vcd
$version Generated by VerilatedVcd $end
$timescale 1ps $end

 $scope module TOP $end
  $var wire  1 % i_a $end
  $var wire  1 & i_b $end
  $var wire  1 # i_clk $end
  $var wire  1 $ i_rst $end
  $var wire  1 ' o_f $end
  $scope module test $end
   $var wire  1 % i_a $end
   $var wire  1 & i_b $end
   $var wire  1 # i_clk $end
   $var wire  1 $ i_rst $end
   $var wire  1 ' o_f $end
   $var wire  1 ( ro_f $end
  $upscope $end
 $upscope $end
$enddefinitions $end


#2
1#
0$
1%
1&
0'
0(
#3
0#
0&
#4
1#
1'
1(
#5
0#
0%
1&
#6
1#
#7
0#
1%
#8
1#
0'
0(
#9
0#
0%
0&
#10
1#
#11
0#
1&
#12
1#
1'
1(
#13
0#
#14
1#
#15
0#
#16
1#
#17
0#
1%
0&
#18
1#
#19
0#
1&
#20
1#
0'
0(
#21
0#
0%
#22
1#
1'
1(
#23
0#
#24
1#
#25
0#
1%
#26
1#
0'
0(
#27
0#
0&
#28
1#
1'
1(
#29
0#
0%
#30
1#
0'
0(
#31
0#
1%
#32
1#
1'
1(
#33
0#
1&
#34
1#
0'
0(
#35
0#
0%
0&
#36
1#
#37
0#
1&
#38
1#
1'
1(
#39
0#
1%
0&
#40
1#
#41
0#
0%
1&
#42
1#
#43
0#
1%
0&
#44
1#
#45
0#
0%
#46
1#
0'
0(
#47
0#
1%
1&
#48
1#
#49
0#
#50
1#
#51
0#
#52
1#
#53
0#
0&
#54
1#
1'
1(
#55
0#
#56
1#
#57
0#
0%
#58
1#
0'
0(
#59
0#
1&
#60
1#
1'
1(
